{"dept":"07","name":"Ardèche","lat":44.77597655943283,"lon":4.353160174482005,"confidence":0.95,"summary":{"global":50,"segments":{"natural":100,"road":50,"air":44,"health":55,"security":85,"flood":3,"wildfire":40,"avalanche":25},"stats":{"max_gust_kmh":131.4,"sum_precip_mm":2.0,"max_aqi":44.0}},"hourly":[{"t":"2026-03-31T03:00","natural":98,"road":49,"air":38,"health":55,"security":85,"flood":0,"wildfire":39,"avalanche":24,"gust_kmh":123.1,"precip_mm":0.1,"temp_c":-0.6,"aqi":38},{"t":"2026-03-31T04:00","natural":100,"road":50,"air":37,"health":55,"security":85,"flood":0,"wildfire":40,"avalanche":25,"gust_kmh":131.0,"precip_mm":0.0,"temp_c":-1.3,"aqi":37},{"t":"2026-03-31T05:00","natural":100,"road":50,"air":37,"health":55,"security":85,"flood":0,"wildfire":40,"avalanche":25,"gust_kmh":131.4,"precip_mm":0.0,"temp_c":-1.7,"aqi":37},{"t":"2026-03-31T06:00","natural":100,"road":50,"air":36,"health":55,"security":85,"flood":0,"wildfire":40,"avalanche":25,"gust_kmh":131.0,"precip_mm":0.0,"temp_c":-1.9,"aqi":36},{"t":"2026-03-31T07:00","natural":100,"road":50,"air":39,"health":55,"security":85,"flood":0,"wildfire":40,"avalanche":25,"gust_kmh":129.6,"precip_mm":0.0,"temp_c":-1.7,"aqi":39},{"t":"2026-03-31T08:00","natural":99,"road":49,"air":38,"health":55,"security":85,"flood":0,"wildfire":40,"avalanche":25,"gust_kmh":124.2,"precip_mm":0.0,"temp_c":-1.3,"aqi":38},{"t":"2026-03-31T09:00","natural":97,"road":48,"air":40,"health":55,"security":85,"flood":0,"wildfire":39,"avalanche":24,"gust_kmh":121.0,"precip_mm":0.0,"temp_c":-0.7,"aqi":40},{"t":"2026-03-31T10:00","natural":96,"road":48,"air":38,"health":30,"security":85,"flood":0,"wildfire":38,"avalanche":24,"gust_kmh":119.5,"precip_mm":0.0,"temp_c":0.2,"aqi":38},{"t":"2026-03-31T11:00","natural":93,"road":46,"air":38,"health":30,"security":85,"flood":0,"wildfire":37,"avalanche":23,"gust_kmh":114.1,"precip_mm":0.0,"temp_c":1.2,"aqi":38},{"t":"2026-03-31T12:00","natural":91,"road":45,"air":41,"health":30,"security":85,"flood":0,"wildfire":36,"avalanche":23,"gust_kmh":109.8,"precip_mm":0.0,"temp_c":2.0,"aqi":41},{"t":"2026-03-31T13:00","natural":90,"road":45,"air":41,"health":30,"security":85,"flood":0,"wildfire":36,"avalanche":22,"gust_kmh":108.0,"precip_mm":0.0,"temp_c":2.3,"aqi":41},{"t":"2026-03-31T14:00","natural":92,"road":46,"air":41,"health":30,"security":85,"flood":0,"wildfire":37,"avalanche":23,"gust_kmh":111.2,"precip_mm":0.0,"temp_c":2.2,"aqi":41},{"t":"2026-03-31T15:00","natural":95,"road":47,"air":41,"health":30,"security":85,"flood":0,"wildfire":38,"avalanche":24,"gust_kmh":117.4,"precip_mm":0.0,"temp_c":2.0,"aqi":41},{"t":"2026-03-31T16:00","natural":95,"road":47,"air":40,"health":30,"security":85,"flood":0,"wildfire":38,"avalanche":24,"gust_kmh":116.6,"precip_mm":0.0,"temp_c":1.2,"aqi":40},{"t":"2026-03-31T17:00","natural":91,"road":45,"air":39,"health":30,"security":85,"flood":0,"wildfire":36,"avalanche":23,"gust_kmh":110.5,"precip_mm":0.0,"temp_c":0.9,"aqi":39},{"t":"2026-03-31T18:00","natural":90,"road":45,"air":38,"health":55,"security":85,"flood":0,"wildfire":36,"avalanche":22,"gust_kmh":107.6,"precip_mm":0.0,"temp_c":-0.1,"aqi":38},{"t":"2026-03-31T19:00","natural":89,"road":44,"air":38,"health":55,"security":85,"flood":0,"wildfire":36,"avalanche":22,"gust_kmh":106.9,"precip_mm":0.0,"temp_c":-0.4,"aqi":38},{"t":"2026-03-31T20:00","natural":85,"road":42,"air":38,"health":55,"security":85,"flood":0,"wildfire":34,"avalanche":21,"gust_kmh":101.5,"precip_mm":0.0,"temp_c":-0.6,"aqi":38},{"t":"2026-03-31T21:00","natural":82,"road":41,"air":37,"health":55,"security":85,"flood":0,"wildfire":33,"avalanche":20,"gust_kmh":99.0,"precip_mm":0.0,"temp_c":-0.7,"aqi":37},{"t":"2026-03-31T22:00","natural":82,"road":41,"air":35,"health":55,"security":85,"flood":0,"wildfire":33,"avalanche":20,"gust_kmh":99.0,"precip_mm":0.0,"temp_c":-1.0,"aqi":35},{"t":"2026-03-31T23:00","natural":81,"road":40,"air":34,"health":55,"security":85,"flood":0,"wildfire":32,"avalanche":20,"gust_kmh":97.6,"precip_mm":0.0,"temp_c":-1.1,"aqi":34},{"t":"2026-04-01T00:00","natural":80,"road":40,"air":34,"health":55,"security":85,"flood":0,"wildfire":32,"avalanche":20,"gust_kmh":95.8,"precip_mm":0.0,"temp_c":-1.4,"aqi":34},{"t":"2026-04-01T01:00","natural":81,"road":40,"air":33,"health":55,"security":85,"flood":0,"wildfire":32,"avalanche":20,"gust_kmh":96.8,"precip_mm":0.0,"temp_c":-1.3,"aqi":33},{"t":"2026-04-01T02:00","natural":81,"road":40,"air":34,"health":55,"security":85,"flood":0,"wildfire":32,"avalanche":20,"gust_kmh":97.2,"precip_mm":0.0,"temp_c":-1.5,"aqi":34},{"t":"2026-04-01T03:00","natural":82,"road":41,"air":32,"health":55,"security":85,"flood":0,"wildfire":33,"avalanche":20,"gust_kmh":98.3,"precip_mm":0.0,"temp_c":-1.5,"aqi":32},{"t":"2026-04-01T04:00","natural":83,"road":41,"air":32,"health":55,"security":85,"flood":0,"wildfire":33,"avalanche":21,"gust_kmh":100.1,"precip_mm":0.0,"temp_c":-1.6,"aqi":32},{"t":"2026-04-01T05:00","natural":85,"road":42,"air":32,"health":55,"security":85,"flood":0,"wildfire":34,"avalanche":21,"gust_kmh":101.5,"precip_mm":0.0,"temp_c":-1.8,"aqi":32},{"t":"2026-04-01T06:00","natural":86,"road":43,"air":31,"health":55,"security":85,"flood":0,"wildfire":34,"avalanche":22,"gust_kmh":102.6,"precip_mm":0.0,"temp_c":-1.8,"aqi":31},{"t":"2026-04-01T07:00","natural":86,"road":43,"air":31,"health":55,"security":85,"flood":0,"wildfire":34,"avalanche":22,"gust_kmh":103.7,"precip_mm":0.0,"temp_c":-1.3,"aqi":31},{"t":"2026-04-01T08:00","natural":88,"road":44,"air":31,"health":55,"security":85,"flood":0,"wildfire":35,"avalanche":22,"gust_kmh":106.2,"precip_mm":0.0,"temp_c":-0.5,"aqi":31},{"t":"2026-04-01T09:00","natural":88,"road":44,"air":32,"health":30,"security":85,"flood":0,"wildfire":35,"avalanche":22,"gust_kmh":106.2,"precip_mm":0.0,"temp_c":0.8,"aqi":32},{"t":"2026-04-01T10:00","natural":86,"road":43,"air":33,"health":30,"security":85,"flood":0,"wildfire":34,"avalanche":22,"gust_kmh":103.0,"precip_mm":0.0,"temp_c":1.9,"aqi":33},{"t":"2026-04-01T11:00","natural":79,"road":39,"air":35,"health":30,"security":85,"flood":0,"wildfire":32,"avalanche":20,"gust_kmh":95.0,"precip_mm":0.0,"temp_c":2.2,"aqi":35},{"t":"2026-04-01T12:00","natural":74,"road":37,"air":37,"health":30,"security":85,"flood":0,"wildfire":30,"avalanche":18,"gust_kmh":88.2,"precip_mm":0.0,"temp_c":4.0,"aqi":37},{"t":"2026-04-01T13:00","natural":69,"road":34,"air":38,"health":30,"security":85,"flood":3,"wildfire":28,"avalanche":17,"gust_kmh":83.2,"precip_mm":0.7,"temp_c":2.9,"aqi":38},{"t":"2026-04-01T14:00","natural":66,"road":33,"air":41,"health":30,"security":85,"flood":2,"wildfire":26,"avalanche":16,"gust_kmh":79.6,"precip_mm":0.4,"temp_c":3.2,"aqi":41},{"t":"2026-04-01T15:00","natural":68,"road":34,"air":44,"health":30,"security":85,"flood":1,"wildfire":27,"avalanche":17,"gust_kmh":82.1,"precip_mm":0.2,"temp_c":3.6,"aqi":44},{"t":"2026-04-01T16:00","natural":71,"road":35,"air":43,"health":30,"security":85,"flood":2,"wildfire":28,"avalanche":18,"gust_kmh":85.3,"precip_mm":0.6,"temp_c":3.1,"aqi":43},{"t":"2026-04-01T17:00","natural":72,"road":36,"air":43,"health":30,"security":85,"flood":0,"wildfire":29,"avalanche":18,"gust_kmh":86.4,"precip_mm":0.0,"temp_c":2.9,"aqi":43},{"t":"2026-04-01T18:00","natural":72,"road":36,"air":42,"health":30,"security":85,"flood":0,"wildfire":29,"avalanche":18,"gust_kmh":86.4,"precip_mm":0.0,"temp_c":2.0,"aqi":42},{"t":"2026-04-01T19:00","natural":66,"road":33,"air":39,"health":30,"security":85,"flood":0,"wildfire":26,"avalanche":16,"gust_kmh":78.8,"precip_mm":0.0,"temp_c":1.1,"aqi":39},{"t":"2026-04-01T20:00","natural":59,"road":29,"air":37,"health":30,"security":85,"flood":0,"wildfire":24,"avalanche":15,"gust_kmh":71.3,"precip_mm":0.0,"temp_c":0.5,"aqi":37},{"t":"2026-04-01T21:00","natural":50,"road":25,"air":37,"health":30,"security":85,"flood":0,"wildfire":20,"avalanche":12,"gust_kmh":63.0,"precip_mm":0.0,"temp_c":0.1,"aqi":37},{"t":"2026-04-01T22:00","natural":51,"road":25,"air":37,"health":30,"security":85,"flood":0,"wildfire":20,"avalanche":13,"gust_kmh":63.6,"precip_mm":0.0,"temp_c":0.4,"aqi":37},{"t":"2026-04-01T23:00","natural":55,"road":27,"air":36,"health":30,"security":85,"flood":0,"wildfire":22,"avalanche":14,"gust_kmh":67.9,"precip_mm":0.0,"temp_c":0.6,"aqi":36},{"t":"2026-04-02T00:00","natural":59,"road":29,"air":35,"health":30,"security":85,"flood":0,"wildfire":24,"avalanche":15,"gust_kmh":71.5,"precip_mm":0.0,"temp_c":0.8,"aqi":35},{"t":"2026-04-02T01:00","natural":63,"road":31,"air":35,"health":30,"security":85,"flood":0,"wildfire":25,"avalanche":16,"gust_kmh":75.6,"precip_mm":0.0,"temp_c":1.1,"aqi":35},{"t":"2026-04-02T02:00","natural":67,"road":33,"air":35,"health":30,"security":85,"flood":0,"wildfire":27,"avalanche":17,"gust_kmh":80.6,"precip_mm":0.0,"temp_c":0.8,"aqi":35},{"t":"2026-04-02T03:00","natural":70,"road":35,"air":36,"health":30,"security":85,"flood":0,"wildfire":28,"avalanche":18,"gust_kmh":83.5,"precip_mm":0.0,"temp_c":0.8,"aqi":36},{"t":"2026-04-02T04:00","natural":75,"road":37,"air":35,"health":30,"security":85,"flood":0,"wildfire":30,"avalanche":19,"gust_kmh":90.0,"precip_mm":0.0,"temp_c":0.6,"aqi":35},{"t":"2026-04-02T05:00","natural":70,"road":35,"air":34,"health":30,"security":85,"flood":0,"wildfire":28,"avalanche":18,"gust_kmh":84.6,"precip_mm":0.0,"temp_c":0.4,"aqi":34},{"t":"2026-04-02T06:00","natural":75,"road":37,"air":35,"health":30,"security":85,"flood":0,"wildfire":30,"avalanche":19,"gust_kmh":90.0,"precip_mm":0.0,"temp_c":0.4,"aqi":35},{"t":"2026-04-02T07:00","natural":78,"road":39,"air":35,"health":30,"security":85,"flood":0,"wildfire":31,"avalanche":20,"gust_kmh":93.2,"precip_mm":0.0,"temp_c":1.3,"aqi":35},{"t":"2026-04-02T08:00","natural":76,"road":38,"air":34,"health":30,"security":85,"flood":0,"wildfire":30,"avalanche":19,"gust_kmh":91.8,"precip_mm":0.0,"temp_c":2.5,"aqi":34},{"t":"2026-04-02T09:00","natural":81,"road":40,"air":34,"health":30,"security":85,"flood":0,"wildfire":32,"avalanche":20,"gust_kmh":97.2,"precip_mm":0.0,"temp_c":3.8,"aqi":34},{"t":"2026-04-02T10:00","natural":82,"road":41,"air":35,"health":21,"security":85,"flood":0,"wildfire":33,"avalanche":20,"gust_kmh":98.3,"precip_mm":0.0,"temp_c":5.1,"aqi":35},{"t":"2026-04-02T11:00","natural":80,"road":40,"air":36,"health":22,"security":85,"flood":0,"wildfire":32,"avalanche":20,"gust_kmh":96.5,"precip_mm":0.0,"temp_c":6.3,"aqi":36},{"t":"2026-04-02T12:00","natural":78,"road":39,"air":36,"health":22,"security":85,"flood":0,"wildfire":31,"avalanche":20,"gust_kmh":93.6,"precip_mm":0.0,"temp_c":7.2,"aqi":36},{"t":"2026-04-02T13:00","natural":78,"road":39,"air":38,"health":23,"security":85,"flood":0,"wildfire":31,"avalanche":20,"gust_kmh":93.6,"precip_mm":0.0,"temp_c":7.7,"aqi":38},{"t":"2026-04-02T14:00","natural":78,"road":39,"air":39,"health":23,"security":85,"flood":0,"wildfire":31,"avalanche":20,"gust_kmh":93.6,"precip_mm":0.0,"temp_c":7.9,"aqi":39},{"t":"2026-04-02T15:00","natural":78,"road":39,"air":40,"health":24,"security":85,"flood":0,"wildfire":31,"avalanche":20,"gust_kmh":93.2,"precip_mm":0.0,"temp_c":7.6,"aqi":40},{"t":"2026-04-02T16:00","natural":78,"road":39,"air":40,"health":24,"security":85,"flood":0,"wildfire":31,"avalanche":20,"gust_kmh":93.6,"precip_mm":0.0,"temp_c":6.7,"aqi":40},{"t":"2026-04-02T17:00","natural":77,"road":38,"air":41,"health":25,"security":85,"flood":0,"wildfire":31,"avalanche":19,"gust_kmh":92.2,"precip_mm":0.0,"temp_c":5.5,"aqi":41},{"t":"2026-04-02T18:00","natural":74,"road":37,"air":41,"health":30,"security":85,"flood":0,"wildfire":30,"avalanche":18,"gust_kmh":88.6,"precip_mm":0.0,"temp_c":4.4,"aqi":41},{"t":"2026-04-02T19:00","natural":68,"road":34,"air":41,"health":30,"security":85,"flood":0,"wildfire":27,"avalanche":17,"gust_kmh":81.7,"precip_mm":0.0,"temp_c":3.6,"aqi":41},{"t":"2026-04-02T20:00","natural":69,"road":34,"air":39,"health":30,"security":85,"flood":0,"wildfire":28,"avalanche":17,"gust_kmh":83.2,"precip_mm":0.0,"temp_c":3.5,"aqi":39},{"t":"2026-04-02T21:00","natural":69,"road":34,"air":38,"health":30,"security":85,"flood":0,"wildfire":28,"avalanche":17,"gust_kmh":83.2,"precip_mm":0.0,"temp_c":3.2,"aqi":38},{"t":"2026-04-02T22:00","natural":73,"road":36,"air":37,"health":30,"security":85,"flood":0,"wildfire":29,"avalanche":18,"gust_kmh":87.8,"precip_mm":0.0,"temp_c":3.1,"aqi":37},{"t":"2026-04-02T23:00","natural":70,"road":35,"air":36,"health":30,"security":85,"flood":0,"wildfire":28,"avalanche":18,"gust_kmh":83.9,"precip_mm":0.0,"temp_c":2.9,"aqi":36},{"t":"2026-04-03T00:00","natural":74,"road":37,"air":36,"health":30,"security":85,"flood":0,"wildfire":30,"avalanche":18,"gust_kmh":88.9,"precip_mm":0.0,"temp_c":2.9,"aqi":36},{"t":"2026-04-03T01:00","natural":73,"road":36,"air":11,"health":30,"security":85,"flood":0,"wildfire":29,"avalanche":18,"gust_kmh":87.8,"precip_mm":0.0,"temp_c":2.8,"aqi":11},{"t":"2026-04-03T02:00","natural":71,"road":35,"air":0,"health":30,"security":85,"flood":0,"wildfire":28,"avalanche":18,"gust_kmh":85.3,"precip_mm":0.0,"temp_c":2.8,"aqi":null}],"security_vigipirate":{"label":"Urgence attentat","score":85,"posture":"hiver-printemps 2026","effective_from":"5 janvier 2026","url":"https://www.sgdsn.gouv.fr/vigipirate","generated_at":"2026-03-31T03:28:19.553344Z","errors":[]},"health_risk":{"generated_at":"2026-03-31T03:28:19.553344Z","source":"Santé publique France / Odissé (SurSaUD: OSCOUR + SOS Médecins) + Open-Meteo (canicule)","as_of":"2026-03-16","confidence":0.15,"confidence_score":15,"confidence_label":"Faible","scores":{"h24":43,"h48":43,"h72":43},"subscores":{"h24":{"severity":51,"exposure":10},"h48":{"severity":51,"exposure":10},"h72":{"severity":51,"exposure":10}},"meta_line":{"h24":"Gastro-entérite: Très élevé · IRA (infections respiratoires aiguës): Élevé · Asthme: Modéré · Bronchiolite (<1 an): Faible","h48":"Gastro-entérite: Très élevé · IRA (infections respiratoires aiguës): Élevé · Asthme: Modéré · Bronchiolite (<1 an): Faible","h72":"Gastro-entérite: Très élevé · IRA (infections respiratoires aiguës): Élevé · Asthme: Modéré · Bronchiolite (<1 an): Faible"},"signals":[{"id":"flu","label":"Grippe/SG","rate":{},"trend":0.0,"score":{"h24":15,"h48":15,"h72":15},"class":{"h24":"Très faible","h48":"Très faible","h72":"Très faible"},"severity_rate":{"h24":0.0,"h48":0.0,"h72":0.0},"severity_score":{"h24":15,"h48":15,"h72":15},"severity_class":{"h24":"Très faible","h48":"Très faible","h72":"Très faible"}},{"id":"gastro","label":"Gastro-entérite","rate":{},"trend":0.0,"score":{"h24":90,"h48":90,"h72":90},"class":{"h24":"Très élevé","h48":"Très élevé","h72":"Très élevé"},"severity_rate":{"h24":2510.46,"h48":2510.46,"h72":2510.46},"severity_score":{"h24":90,"h48":90,"h72":90},"severity_class":{"h24":"Très élevé","h48":"Très élevé","h72":"Très élevé"}},{"id":"bronchio","label":"Bronchiolite (<1 an)","rate":{},"trend":0.0,"score":{"h24":32,"h48":32,"h72":32},"class":{"h24":"Faible","h48":"Faible","h72":"Faible"},"severity_rate":{"h24":14285.714,"h48":14285.714,"h72":14285.714},"severity_score":{"h24":32,"h48":32,"h72":32},"severity_class":{"h24":"Faible","h48":"Faible","h72":"Faible"}},{"id":"covid","label":"COVID-19 (suspicion)","rate":{},"trend":0.0,"score":{"h24":15,"h48":15,"h72":15},"class":{"h24":"Très faible","h48":"Très faible","h72":"Très faible"},"severity_rate":{"h24":0.0,"h48":0.0,"h72":0.0},"severity_score":{"h24":15,"h48":15,"h72":15},"severity_class":{"h24":"Très faible","h48":"Très faible","h72":"Très faible"}},{"id":"ira","label":"IRA (infections respiratoires aiguës)","rate":{},"trend":0.0,"score":{"h24":72,"h48":72,"h72":72},"class":{"h24":"Élevé","h48":"Élevé","h72":"Élevé"},"severity_rate":{"h24":6694.561,"h48":6694.561,"h72":6694.561},"severity_score":{"h24":72,"h48":72,"h72":72},"severity_class":{"h24":"Élevé","h48":"Élevé","h72":"Élevé"}},{"id":"asthma","label":"Asthme","rate":{},"trend":0.0,"score":{"h24":52,"h48":52,"h72":52},"class":{"h24":"Modéré","h48":"Modéré","h72":"Modéré"},"severity_rate":{"h24":1255.23,"h48":1255.23,"h72":1255.23},"severity_score":{"h24":52,"h48":52,"h72":52},"severity_class":{"h24":"Modéré","h48":"Modéré","h72":"Modéré"}},{"id":"heatwave","label":"Canicule","max_temp_c":{"h24":2.3,"h48":4.0,"h72":7.9},"min_temp_c":{"h24":-1.9,"h48":-1.8,"h72":0.4},"score":{"h24":10,"h48":10,"h72":10},"class":{"h24":"Très faible","h48":"Très faible","h72":"Très faible"}}],"details":{"flu":{"label":"Grippe/SG","score":15,"label_h24":"Très faible","severity_score":15},"gastro":{"label":"Gastro-entérite","score":90,"label_h24":"Très élevé","severity_score":90},"bronchio":{"label":"Bronchiolite (<1 an)","score":32,"label_h24":"Faible","severity_score":32},"covid":{"label":"COVID-19 (suspicion)","score":15,"label_h24":"Très faible","severity_score":15},"ira":{"label":"IRA (infections respiratoires aiguës)","score":72,"label_h24":"Élevé","severity_score":72},"asthma":{"label":"Asthme","score":52,"label_h24":"Modéré","severity_score":52},"heatwave":{"label":"Canicule","score":10,"label_h24":"Très faible"}},"reasons":["Basé sur la surveillance syndromique SurSaUD® (OSCOUR + SOS Médecins) via Odissé (SPF).","Données les plus récentes : 2026-03-16 (J+1 puis consolidation).","Signal dominant : Gastro-entérite.","Plusieurs signaux reposent surtout sur la gravité hospitalière ; les taux observés sont partiels ou absents pour ce département.","Canicule : calcul court-terme basé sur la prévision de température (Open-Meteo).","Le score de confiance est abaissé quand les taux observés sont incomplets et que l'évaluation repose surtout sur la gravité hospitalière."],"tips":["En cas de symptômes : limite les contacts, aère, et surveille l’évolution.","Si tu es fragile (âge, comorbidités) : anticipe (masque/gel, éviter les lieux clos bondés).","Consulte un professionnel si les symptômes s’aggravent ou persistent.","En cas de fortes chaleurs : hydrate-toi, évite les efforts aux heures chaudes, et privilégie un lieu frais."]},"route_conditions":{"generated_at":"2026-03-31T03:28:59.908240+00:00","updated_at":null,"sources":{"traffic_events":"https://transport.data.gouv.fr/resources/79175/download","jams":"https://transport.data.gouv.fr/resources/79176/download","works_current":"https://transport.data.gouv.fr/resources/79177/download","works_planned":"https://transport.data.gouv.fr/resources/79178/download","datex_events":"https://transport.data.gouv.fr/resources/79174/download"},"counts":{"traffic_events":{"count":0,"stars":0},"jams":{"count":0,"stars":0},"works_current":{"count":1,"stars":2},"works_planned":{"count":0,"stars":0,"by_horizon":{"h24":0,"h48":0,"h72":0},"by_horizon_stars":{"h24":0,"h48":0,"h72":0}}},"scores":{"h24":5,"h48":3,"h72":2},"top":["Travaux: 1"]},"fire_danger":{"generated_at":"2026-03-31T03:28:19.553344Z","source":"FWI (Canadian) calculé depuis Open-Meteo","fwi":{"h24":13.2,"h48":9.3,"h72":3.3},"class":{"h24":"Modéré","h48":"Faible","h72":"Très faible"},"score":{"h24":22,"h48":15,"h72":6},"method":"cffwis_v1"},"avalanche_bra":{"concerned":false}}