{"dept":"87","name":"Haute-Vienne","lat":45.89867336200443,"lon":1.2495407778608831,"confidence":0.75,"summary":{"global":16,"segments":{"natural":16,"road":8,"air":0,"health":0,"security":85,"flood":5,"wildfire":6,"avalanche":4},"stats":{"max_gust_kmh":29.2,"sum_precip_mm":7.5,"max_aqi":0.0}},"hourly":[{"t":"2026-05-07T14:00","natural":6,"road":3,"air":0,"health":0,"security":85,"flood":0,"wildfire":2,"avalanche":2,"gust_kmh":11.2,"precip_mm":0.0,"temp_c":16.3,"aqi":null},{"t":"2026-05-07T15:00","natural":8,"road":4,"air":0,"health":0,"security":85,"flood":0,"wildfire":3,"avalanche":2,"gust_kmh":13.7,"precip_mm":0.0,"temp_c":16.1,"aqi":null},{"t":"2026-05-07T16:00","natural":6,"road":3,"air":0,"health":0,"security":85,"flood":1,"wildfire":2,"avalanche":2,"gust_kmh":11.2,"precip_mm":0.2,"temp_c":15.1,"aqi":null},{"t":"2026-05-07T17:00","natural":4,"road":2,"air":0,"health":0,"security":85,"flood":0,"wildfire":2,"avalanche":1,"gust_kmh":6.8,"precip_mm":0.0,"temp_c":15.9,"aqi":null},{"t":"2026-05-07T18:00","natural":8,"road":4,"air":0,"health":0,"security":85,"flood":0,"wildfire":3,"avalanche":2,"gust_kmh":14.0,"precip_mm":0.0,"temp_c":15.2,"aqi":null},{"t":"2026-05-07T19:00","natural":6,"road":3,"air":0,"health":0,"security":85,"flood":0,"wildfire":2,"avalanche":2,"gust_kmh":11.5,"precip_mm":0.0,"temp_c":14.0,"aqi":null},{"t":"2026-05-07T20:00","natural":4,"road":2,"air":0,"health":0,"security":85,"flood":0,"wildfire":2,"avalanche":1,"gust_kmh":7.9,"precip_mm":0.0,"temp_c":13.2,"aqi":null},{"t":"2026-05-07T21:00","natural":5,"road":2,"air":0,"health":0,"security":85,"flood":0,"wildfire":2,"avalanche":1,"gust_kmh":8.3,"precip_mm":0.0,"temp_c":12.3,"aqi":null},{"t":"2026-05-07T22:00","natural":5,"road":2,"air":0,"health":0,"security":85,"flood":0,"wildfire":2,"avalanche":1,"gust_kmh":9.0,"precip_mm":0.0,"temp_c":11.5,"aqi":null},{"t":"2026-05-07T23:00","natural":6,"road":3,"air":0,"health":0,"security":85,"flood":0,"wildfire":2,"avalanche":2,"gust_kmh":10.1,"precip_mm":0.0,"temp_c":10.8,"aqi":null},{"t":"2026-05-08T00:00","natural":6,"road":3,"air":0,"health":0,"security":85,"flood":0,"wildfire":2,"avalanche":2,"gust_kmh":10.4,"precip_mm":0.0,"temp_c":10.1,"aqi":null},{"t":"2026-05-08T01:00","natural":6,"road":3,"air":0,"health":0,"security":85,"flood":0,"wildfire":2,"avalanche":2,"gust_kmh":11.5,"precip_mm":0.0,"temp_c":9.6,"aqi":null},{"t":"2026-05-08T02:00","natural":6,"road":3,"air":0,"health":0,"security":85,"flood":0,"wildfire":2,"avalanche":2,"gust_kmh":10.4,"precip_mm":0.0,"temp_c":9.5,"aqi":null},{"t":"2026-05-08T03:00","natural":5,"road":2,"air":0,"health":0,"security":85,"flood":0,"wildfire":2,"avalanche":1,"gust_kmh":9.0,"precip_mm":0.0,"temp_c":9.4,"aqi":null},{"t":"2026-05-08T04:00","natural":4,"road":2,"air":0,"health":0,"security":85,"flood":0,"wildfire":2,"avalanche":1,"gust_kmh":6.8,"precip_mm":0.0,"temp_c":9.0,"aqi":null},{"t":"2026-05-08T05:00","natural":3,"road":1,"air":0,"health":0,"security":85,"flood":0,"wildfire":1,"avalanche":1,"gust_kmh":6.1,"precip_mm":0.0,"temp_c":8.5,"aqi":null},{"t":"2026-05-08T06:00","natural":4,"road":2,"air":0,"health":0,"security":85,"flood":0,"wildfire":2,"avalanche":1,"gust_kmh":7.6,"precip_mm":0.0,"temp_c":9.7,"aqi":null},{"t":"2026-05-08T07:00","natural":6,"road":3,"air":0,"health":0,"security":85,"flood":0,"wildfire":2,"avalanche":2,"gust_kmh":10.8,"precip_mm":0.0,"temp_c":12.0,"aqi":null},{"t":"2026-05-08T08:00","natural":7,"road":3,"air":0,"health":0,"security":85,"flood":0,"wildfire":3,"avalanche":2,"gust_kmh":13.3,"precip_mm":0.0,"temp_c":14.3,"aqi":null},{"t":"2026-05-08T09:00","natural":8,"road":4,"air":0,"health":0,"security":85,"flood":0,"wildfire":3,"avalanche":2,"gust_kmh":14.0,"precip_mm":0.0,"temp_c":16.5,"aqi":null},{"t":"2026-05-08T10:00","natural":8,"road":4,"air":0,"health":0,"security":85,"flood":0,"wildfire":3,"avalanche":2,"gust_kmh":14.8,"precip_mm":0.0,"temp_c":18.1,"aqi":null},{"t":"2026-05-08T11:00","natural":10,"road":5,"air":0,"health":0,"security":85,"flood":0,"wildfire":4,"avalanche":2,"gust_kmh":18.4,"precip_mm":0.0,"temp_c":19.6,"aqi":null},{"t":"2026-05-08T12:00","natural":10,"road":5,"air":0,"health":0,"security":85,"flood":0,"wildfire":4,"avalanche":2,"gust_kmh":18.4,"precip_mm":0.0,"temp_c":20.5,"aqi":null},{"t":"2026-05-08T13:00","natural":8,"road":4,"air":0,"health":0,"security":85,"flood":0,"wildfire":3,"avalanche":2,"gust_kmh":14.8,"precip_mm":0.0,"temp_c":21.1,"aqi":null},{"t":"2026-05-08T14:00","natural":7,"road":3,"air":0,"health":0,"security":85,"flood":0,"wildfire":3,"avalanche":2,"gust_kmh":13.3,"precip_mm":0.0,"temp_c":21.5,"aqi":null},{"t":"2026-05-08T15:00","natural":8,"road":4,"air":0,"health":0,"security":85,"flood":0,"wildfire":3,"avalanche":2,"gust_kmh":14.4,"precip_mm":0.0,"temp_c":21.4,"aqi":null},{"t":"2026-05-08T16:00","natural":8,"road":4,"air":0,"health":0,"security":85,"flood":0,"wildfire":3,"avalanche":2,"gust_kmh":14.4,"precip_mm":0.0,"temp_c":21.3,"aqi":null},{"t":"2026-05-08T17:00","natural":5,"road":2,"air":0,"health":0,"security":85,"flood":0,"wildfire":2,"avalanche":1,"gust_kmh":8.6,"precip_mm":0.0,"temp_c":21.0,"aqi":null},{"t":"2026-05-08T18:00","natural":2,"road":1,"air":0,"health":0,"security":85,"flood":0,"wildfire":1,"avalanche":0,"gust_kmh":4.0,"precip_mm":0.0,"temp_c":19.8,"aqi":null},{"t":"2026-05-08T19:00","natural":3,"road":1,"air":0,"health":0,"security":85,"flood":0,"wildfire":1,"avalanche":1,"gust_kmh":5.4,"precip_mm":0.0,"temp_c":18.0,"aqi":null},{"t":"2026-05-08T20:00","natural":8,"road":4,"air":0,"health":0,"security":85,"flood":0,"wildfire":3,"avalanche":2,"gust_kmh":13.7,"precip_mm":0.0,"temp_c":17.0,"aqi":null},{"t":"2026-05-08T21:00","natural":7,"road":3,"air":0,"health":0,"security":85,"flood":0,"wildfire":3,"avalanche":2,"gust_kmh":13.3,"precip_mm":0.0,"temp_c":15.6,"aqi":null},{"t":"2026-05-08T22:00","natural":8,"road":4,"air":0,"health":0,"security":85,"flood":2,"wildfire":3,"avalanche":2,"gust_kmh":13.7,"precip_mm":0.3,"temp_c":15.4,"aqi":null},{"t":"2026-05-08T23:00","natural":8,"road":4,"air":0,"health":0,"security":85,"flood":0,"wildfire":3,"avalanche":2,"gust_kmh":13.7,"precip_mm":0.0,"temp_c":14.4,"aqi":null},{"t":"2026-05-09T00:00","natural":6,"road":3,"air":0,"health":0,"security":85,"flood":0,"wildfire":2,"avalanche":2,"gust_kmh":10.1,"precip_mm":0.0,"temp_c":13.7,"aqi":null},{"t":"2026-05-09T01:00","natural":6,"road":3,"air":0,"health":0,"security":85,"flood":0,"wildfire":2,"avalanche":2,"gust_kmh":10.1,"precip_mm":0.0,"temp_c":13.1,"aqi":null},{"t":"2026-05-09T02:00","natural":6,"road":3,"air":0,"health":0,"security":85,"flood":0,"wildfire":2,"avalanche":2,"gust_kmh":11.5,"precip_mm":0.0,"temp_c":12.0,"aqi":null},{"t":"2026-05-09T03:00","natural":6,"road":3,"air":0,"health":0,"security":85,"flood":0,"wildfire":2,"avalanche":2,"gust_kmh":10.8,"precip_mm":0.0,"temp_c":11.3,"aqi":null},{"t":"2026-05-09T04:00","natural":5,"road":2,"air":0,"health":0,"security":85,"flood":0,"wildfire":2,"avalanche":1,"gust_kmh":9.7,"precip_mm":0.0,"temp_c":10.6,"aqi":null},{"t":"2026-05-09T05:00","natural":5,"road":2,"air":0,"health":0,"security":85,"flood":0,"wildfire":2,"avalanche":1,"gust_kmh":9.0,"precip_mm":0.0,"temp_c":9.9,"aqi":null},{"t":"2026-05-09T06:00","natural":6,"road":3,"air":0,"health":0,"security":85,"flood":0,"wildfire":2,"avalanche":2,"gust_kmh":11.2,"precip_mm":0.0,"temp_c":11.0,"aqi":null},{"t":"2026-05-09T07:00","natural":9,"road":4,"air":0,"health":0,"security":85,"flood":0,"wildfire":4,"avalanche":2,"gust_kmh":16.2,"precip_mm":0.0,"temp_c":12.9,"aqi":null},{"t":"2026-05-09T08:00","natural":12,"road":6,"air":0,"health":0,"security":85,"flood":0,"wildfire":5,"avalanche":3,"gust_kmh":21.2,"precip_mm":0.0,"temp_c":15.0,"aqi":null},{"t":"2026-05-09T09:00","natural":13,"road":6,"air":0,"health":0,"security":85,"flood":0,"wildfire":5,"avalanche":3,"gust_kmh":22.7,"precip_mm":0.0,"temp_c":16.6,"aqi":null},{"t":"2026-05-09T10:00","natural":13,"road":6,"air":0,"health":0,"security":85,"flood":0,"wildfire":5,"avalanche":3,"gust_kmh":24.0,"precip_mm":0.0,"temp_c":18.1,"aqi":null},{"t":"2026-05-09T11:00","natural":14,"road":7,"air":0,"health":0,"security":85,"flood":0,"wildfire":6,"avalanche":4,"gust_kmh":25.4,"precip_mm":0.0,"temp_c":19.5,"aqi":null},{"t":"2026-05-09T12:00","natural":14,"road":7,"air":0,"health":0,"security":85,"flood":0,"wildfire":6,"avalanche":4,"gust_kmh":25.5,"precip_mm":0.0,"temp_c":20.6,"aqi":null},{"t":"2026-05-09T13:00","natural":16,"road":8,"air":0,"health":0,"security":85,"flood":0,"wildfire":6,"avalanche":4,"gust_kmh":28.8,"precip_mm":0.0,"temp_c":20.9,"aqi":null},{"t":"2026-05-09T14:00","natural":16,"road":8,"air":0,"health":0,"security":85,"flood":0,"wildfire":6,"avalanche":4,"gust_kmh":29.2,"precip_mm":0.0,"temp_c":21.7,"aqi":null},{"t":"2026-05-09T15:00","natural":11,"road":5,"air":0,"health":0,"security":85,"flood":0,"wildfire":4,"avalanche":3,"gust_kmh":20.5,"precip_mm":0.0,"temp_c":22.1,"aqi":null},{"t":"2026-05-09T16:00","natural":11,"road":5,"air":0,"health":0,"security":85,"flood":0,"wildfire":4,"avalanche":3,"gust_kmh":19.4,"precip_mm":0.0,"temp_c":21.8,"aqi":null},{"t":"2026-05-09T17:00","natural":10,"road":5,"air":0,"health":0,"security":85,"flood":0,"wildfire":4,"avalanche":2,"gust_kmh":18.0,"precip_mm":0.0,"temp_c":21.4,"aqi":null},{"t":"2026-05-09T18:00","natural":10,"road":5,"air":0,"health":0,"security":85,"flood":0,"wildfire":4,"avalanche":2,"gust_kmh":17.6,"precip_mm":0.0,"temp_c":20.6,"aqi":null},{"t":"2026-05-09T19:00","natural":11,"road":5,"air":0,"health":0,"security":85,"flood":0,"wildfire":4,"avalanche":3,"gust_kmh":20.5,"precip_mm":0.0,"temp_c":19.4,"aqi":null},{"t":"2026-05-09T20:00","natural":9,"road":4,"air":0,"health":0,"security":85,"flood":0,"wildfire":4,"avalanche":2,"gust_kmh":16.2,"precip_mm":0.0,"temp_c":18.0,"aqi":null},{"t":"2026-05-09T21:00","natural":7,"road":3,"air":0,"health":0,"security":85,"flood":0,"wildfire":3,"avalanche":2,"gust_kmh":12.6,"precip_mm":0.0,"temp_c":17.1,"aqi":null},{"t":"2026-05-09T22:00","natural":3,"road":1,"air":0,"health":0,"security":85,"flood":0,"wildfire":1,"avalanche":1,"gust_kmh":5.4,"precip_mm":0.0,"temp_c":16.3,"aqi":null},{"t":"2026-05-09T23:00","natural":3,"road":1,"air":0,"health":0,"security":85,"flood":0,"wildfire":1,"avalanche":1,"gust_kmh":5.0,"precip_mm":0.0,"temp_c":15.2,"aqi":null},{"t":"2026-05-10T00:00","natural":2,"road":1,"air":0,"health":0,"security":85,"flood":0,"wildfire":1,"avalanche":0,"gust_kmh":4.3,"precip_mm":0.0,"temp_c":14.3,"aqi":null},{"t":"2026-05-10T01:00","natural":3,"road":1,"air":0,"health":0,"security":85,"flood":0,"wildfire":1,"avalanche":1,"gust_kmh":4.7,"precip_mm":0.0,"temp_c":13.9,"aqi":null},{"t":"2026-05-10T02:00","natural":5,"road":2,"air":0,"health":0,"security":85,"flood":0,"wildfire":2,"avalanche":1,"gust_kmh":8.3,"precip_mm":0.0,"temp_c":13.3,"aqi":null},{"t":"2026-05-10T03:00","natural":5,"road":2,"air":0,"health":0,"security":85,"flood":0,"wildfire":2,"avalanche":1,"gust_kmh":8.6,"precip_mm":0.0,"temp_c":13.3,"aqi":null},{"t":"2026-05-10T04:00","natural":5,"road":2,"air":0,"health":0,"security":85,"flood":0,"wildfire":2,"avalanche":1,"gust_kmh":9.0,"precip_mm":0.0,"temp_c":13.2,"aqi":null},{"t":"2026-05-10T05:00","natural":5,"road":2,"air":0,"health":0,"security":85,"flood":0,"wildfire":2,"avalanche":1,"gust_kmh":9.4,"precip_mm":0.1,"temp_c":13.0,"aqi":null},{"t":"2026-05-10T06:00","natural":7,"road":3,"air":0,"health":0,"security":85,"flood":2,"wildfire":3,"avalanche":2,"gust_kmh":13.0,"precip_mm":0.6,"temp_c":12.8,"aqi":null},{"t":"2026-05-10T07:00","natural":7,"road":3,"air":0,"health":0,"security":85,"flood":2,"wildfire":3,"avalanche":2,"gust_kmh":11.9,"precip_mm":0.6,"temp_c":12.9,"aqi":null},{"t":"2026-05-10T08:00","natural":8,"road":5,"air":0,"health":0,"security":85,"flood":4,"wildfire":3,"avalanche":2,"gust_kmh":14.8,"precip_mm":1.0,"temp_c":13.2,"aqi":null},{"t":"2026-05-10T09:00","natural":8,"road":4,"air":0,"health":0,"security":85,"flood":3,"wildfire":3,"avalanche":2,"gust_kmh":14.8,"precip_mm":0.9,"temp_c":13.4,"aqi":null},{"t":"2026-05-10T10:00","natural":7,"road":4,"air":0,"health":0,"security":85,"flood":3,"wildfire":3,"avalanche":2,"gust_kmh":11.9,"precip_mm":0.8,"temp_c":13.7,"aqi":null},{"t":"2026-05-10T11:00","natural":5,"road":4,"air":0,"health":0,"security":85,"flood":3,"wildfire":2,"avalanche":1,"gust_kmh":8.3,"precip_mm":0.8,"temp_c":13.9,"aqi":null},{"t":"2026-05-10T12:00","natural":6,"road":6,"air":0,"health":0,"security":85,"flood":5,"wildfire":2,"avalanche":1,"gust_kmh":8.3,"precip_mm":1.2,"temp_c":14.0,"aqi":null},{"t":"2026-05-10T13:00","natural":5,"road":5,"air":0,"health":0,"security":85,"flood":4,"wildfire":2,"avalanche":1,"gust_kmh":9.4,"precip_mm":1.0,"temp_c":14.1,"aqi":null}],"security_vigipirate":{"label":"Urgence attentat","score":85,"posture":"hiver-printemps 2026","effective_from":"5 janvier 2026","url":"https://www.sgdsn.gouv.fr/vigipirate","generated_at":"2026-05-07T14:47:28.935304Z","errors":[]},"health_risk":{"generated_at":"2026-05-07T14:47:28.935304Z","source":"Santé publique France / Odissé (SurSaUD: OSCOUR + SOS Médecins) + Open-Meteo (canicule)","as_of":"2026-04-27","confidence":0.9,"confidence_score":90,"confidence_label":"Élevée","scores":{"h24":43,"h48":43,"h72":43},"subscores":{"h24":{"observed":58,"severity":37,"exposure":10},"h48":{"observed":58,"severity":37,"exposure":10},"h72":{"observed":58,"severity":37,"exposure":10}},"meta_line":{"h24":"Bronchiolite (<1 an): Élevé · Gastro-entérite: Modéré · IRA (infections respiratoires aiguës): Modéré · Grippe/SG: Modéré","h48":"Bronchiolite (<1 an): Élevé · Gastro-entérite: Modéré · IRA (infections respiratoires aiguës): Modéré · Grippe/SG: Modéré","h72":"Bronchiolite (<1 an): Élevé · Gastro-entérite: Modéré · IRA (infections respiratoires aiguës): Modéré · Grippe/SG: Modéré"},"signals":[{"id":"flu","label":"Grippe/SG","rate":{"h24":1772.002,"h48":1772.002,"h72":1772.002},"trend":0.0,"score":{"h24":52,"h48":52,"h72":52},"class":{"h24":"Modéré","h48":"Modéré","h72":"Modéré"},"severity_rate":{"h24":0.0,"h48":0.0,"h72":0.0},"severity_score":{"h24":15,"h48":15,"h72":15},"severity_class":{"h24":"Très faible","h48":"Très faible","h72":"Très faible"}},{"id":"gastro","label":"Gastro-entérite","rate":{"h24":7678.677,"h48":7678.677,"h72":7678.677},"trend":0.0,"score":{"h24":58,"h48":58,"h72":58},"class":{"h24":"Modéré","h48":"Modéré","h72":"Modéré"},"severity_rate":{"h24":777.605,"h48":777.605,"h72":777.605},"severity_score":{"h24":32,"h48":32,"h72":32},"severity_class":{"h24":"Faible","h48":"Faible","h72":"Faible"}},{"id":"bronchio","label":"Bronchiolite (<1 an)","rate":{"h24":17391.304,"h48":17391.304,"h72":17391.304},"trend":0.0,"score":{"h24":77,"h48":77,"h72":77},"class":{"h24":"Élevé","h48":"Élevé","h72":"Élevé"},"severity_rate":{"h24":12500.0,"h48":12500.0,"h72":12500.0},"severity_score":{"h24":52,"h48":52,"h72":52},"severity_class":{"h24":"Modéré","h48":"Modéré","h72":"Modéré"}},{"id":"covid","label":"COVID-19 (suspicion)","rate":{"h24":0.0,"h48":0.0,"h72":0.0},"trend":0.0,"score":{"h24":15,"h48":15,"h72":15},"class":{"h24":"Très faible","h48":"Très faible","h72":"Très faible"},"severity_rate":{"h24":0.0,"h48":0.0,"h72":0.0},"severity_score":{"h24":15,"h48":15,"h72":15},"severity_class":{"h24":"Très faible","h48":"Très faible","h72":"Très faible"}},{"id":"ira","label":"IRA (infections respiratoires aiguës)","rate":{"h24":6024.808,"h48":6024.808,"h72":6024.808},"trend":0.0,"score":{"h24":58,"h48":58,"h72":58},"class":{"h24":"Modéré","h48":"Modéré","h72":"Modéré"},"severity_rate":{"h24":4043.546,"h48":4043.546,"h72":4043.546},"severity_score":{"h24":32,"h48":32,"h72":32},"severity_class":{"h24":"Faible","h48":"Faible","h72":"Faible"}},{"id":"asthma","label":"Asthme","rate":{"h24":767.868,"h48":767.868,"h72":767.868},"trend":0.0,"score":{"h24":52,"h48":52,"h72":52},"class":{"h24":"Modéré","h48":"Modéré","h72":"Modéré"},"severity_rate":{"h24":1399.689,"h48":1399.689,"h72":1399.689},"severity_score":{"h24":90,"h48":90,"h72":90},"severity_class":{"h24":"Très élevé","h48":"Très élevé","h72":"Très élevé"}},{"id":"heatwave","label":"Canicule","max_temp_c":{"h24":21.1,"h48":21.5,"h72":22.1},"min_temp_c":{"h24":8.5,"h48":9.9,"h72":12.8},"score":{"h24":10,"h48":10,"h72":10},"class":{"h24":"Très faible","h48":"Très faible","h72":"Très faible"}}],"details":{"flu":{"label":"Grippe/SG","score":52,"label_h24":"Modéré","observed_score":72,"severity_score":15},"gastro":{"label":"Gastro-entérite","score":58,"label_h24":"Modéré","observed_score":90,"severity_score":32},"bronchio":{"label":"Bronchiolite (<1 an)","score":77,"label_h24":"Élevé","observed_score":90,"severity_score":52},"covid":{"label":"COVID-19 (suspicion)","score":15,"label_h24":"Très faible","observed_score":15,"severity_score":15},"ira":{"label":"IRA (infections respiratoires aiguës)","score":58,"label_h24":"Modéré","observed_score":72,"severity_score":32},"asthma":{"label":"Asthme","score":52,"label_h24":"Modéré","observed_score":32,"severity_score":90},"heatwave":{"label":"Canicule","score":10,"label_h24":"Très faible"}},"reasons":["Basé sur la surveillance syndromique SurSaUD® (OSCOUR + SOS Médecins) via Odissé (SPF).","Données les plus récentes : 2026-04-27 (J+1 puis consolidation).","Signal dominant : Bronchiolite (<1 an).","Canicule : calcul court-terme basé sur la prévision de température (Open-Meteo)."],"tips":["En cas de symptômes : limite les contacts, aère, et surveille l’évolution.","Si tu es fragile (âge, comorbidités) : anticipe (masque/gel, éviter les lieux clos bondés).","Consulte un professionnel si les symptômes s’aggravent ou persistent.","En cas de fortes chaleurs : hydrate-toi, évite les efforts aux heures chaudes, et privilégie un lieu frais."]},"route_conditions":{"generated_at":"2026-05-07T14:47:50.168831+00:00","updated_at":null,"sources":{"traffic_events":"https://transport.data.gouv.fr/resources/79175/download","jams":"https://transport.data.gouv.fr/resources/79176/download","works_current":"https://transport.data.gouv.fr/resources/79177/download","works_planned":"https://transport.data.gouv.fr/resources/79178/download","datex_events":"https://transport.data.gouv.fr/resources/79174/download"},"counts":{"traffic_events":{"count":3,"stars":6},"jams":{"count":0,"stars":0},"works_current":{"count":3,"stars":7},"works_planned":{"count":0,"stars":0,"by_horizon":{"h24":0,"h48":0,"h72":0},"by_horizon_stars":{"h24":0,"h48":0,"h72":0}}},"scores":{"h24":56,"h48":26,"h72":20},"top":["Incidents: 3","Travaux: 3"]},"fire_danger":{"generated_at":"2026-05-07T14:47:28.935304Z","source":"FWI (Canadian) calculé depuis Open-Meteo","fwi":{"h24":2.9,"h48":5.2,"h72":6.5},"class":{"h24":"Très faible","h48":"Faible","h72":"Faible"},"score":{"h24":5,"h48":9,"h72":11},"method":"cffwis_v1"},"avalanche_bra":{"concerned":false}}