{"generated_at":"2026-06-05T10:13:41.175617Z","source":"Bison Futé / TIPI (transport.data.gouv.fr recaps)","errors":[],"depts_detected":89,"top_depts_h24":[{"dept":"01","score":100,"top":["Incidents: 11","Travaux: 3"]},{"dept":"05","score":100,"top":["Incidents: 40","Travaux: 3","Prévu (24h): 1"]},{"dept":"06","score":100,"top":["Bouchons: 5","Incidents: 2","Travaux: 3"]},{"dept":"13","score":100,"top":["Incidents: 10","Travaux: 10"]},{"dept":"18","score":100,"top":["Incidents: 5","Travaux: 5"]},{"dept":"25","score":100,"top":["Bouchons: 1","Incidents: 7","Travaux: 5"]},{"dept":"28","score":100,"top":["Incidents: 7","Travaux: 10"]},{"dept":"33","score":100,"top":["Bouchons: 1","Incidents: 8","Travaux: 10"]},{"dept":"34","score":100,"top":["Bouchons: 1","Incidents: 9","Travaux: 6"]},{"dept":"38","score":100,"top":["Bouchons: 3","Incidents: 6","Travaux: 6"]},{"dept":"42","score":100,"top":["Incidents: 6","Travaux: 10"]},{"dept":"61","score":100,"top":["Incidents: 13"]},{"dept":"63","score":100,"top":["Incidents: 6","Travaux: 9"]},{"dept":"69","score":100,"top":["Bouchons: 8","Incidents: 8","Travaux: 7"]},{"dept":"71","score":100,"top":["Incidents: 11","Travaux: 13"]},{"dept":"72","score":100,"top":["Incidents: 6","Travaux: 7"]},{"dept":"73","score":100,"top":["Incidents: 14","Travaux: 5"]},{"dept":"74","score":100,"top":["Incidents: 5","Travaux: 13"]},{"dept":"77","score":100,"top":["Incidents: 6","Travaux: 7"]},{"dept":"89","score":100,"top":["Incidents: 8","Travaux: 7"]}],"top_depts_h48":[{"dept":"05","score":100,"top":["Incidents: 40","Travaux: 3","Prévu (24h): 1"]},{"dept":"71","score":97,"top":["Incidents: 11","Travaux: 13"]},{"dept":"69","score":92,"top":["Bouchons: 8","Incidents: 8","Travaux: 7"]},{"dept":"33","score":78,"top":["Bouchons: 1","Incidents: 8","Travaux: 10"]},{"dept":"74","score":76,"top":["Incidents: 5","Travaux: 13"]},{"dept":"25","score":67,"top":["Bouchons: 1","Incidents: 7","Travaux: 5"]},{"dept":"01","score":66,"top":["Incidents: 11","Travaux: 3"]},{"dept":"13","score":65,"top":["Incidents: 10","Travaux: 10"]},{"dept":"38","score":60,"top":["Bouchons: 3","Incidents: 6","Travaux: 6"]},{"dept":"63","score":60,"top":["Incidents: 6","Travaux: 9"]},{"dept":"89","score":60,"top":["Incidents: 8","Travaux: 7"]},{"dept":"73","score":59,"top":["Incidents: 14","Travaux: 5"]},{"dept":"28","score":58,"top":["Incidents: 7","Travaux: 10"]},{"dept":"42","score":58,"top":["Incidents: 6","Travaux: 10"]},{"dept":"34","score":56,"top":["Bouchons: 1","Incidents: 9","Travaux: 6"]},{"dept":"48","score":55,"top":["Incidents: 4","Travaux: 7","Prévu (24h): 3"]},{"dept":"77","score":52,"top":["Incidents: 6","Travaux: 7"]},{"dept":"31","score":50,"top":["Bouchons: 1","Incidents: 2","Travaux: 10"]},{"dept":"30","score":47,"top":["Bouchons: 1","Incidents: 3","Travaux: 4"]},{"dept":"06","score":46,"top":["Bouchons: 5","Incidents: 2","Travaux: 3"]}],"top_depts_h72":[{"dept":"05","score":100,"top":["Incidents: 40","Travaux: 3","Prévu (24h): 1"]},{"dept":"71","score":84,"top":["Incidents: 11","Travaux: 13"]},{"dept":"69","score":73,"top":["Bouchons: 8","Incidents: 8","Travaux: 7"]},{"dept":"33","score":68,"top":["Bouchons: 1","Incidents: 8","Travaux: 10"]},{"dept":"25","score":62,"top":["Bouchons: 1","Incidents: 7","Travaux: 5"]},{"dept":"74","score":61,"top":["Incidents: 5","Travaux: 13"]},{"dept":"01","score":53,"top":["Incidents: 11","Travaux: 3"]},{"dept":"13","score":52,"top":["Incidents: 10","Travaux: 10"]},{"dept":"04","score":51,"top":["Incidents: 3","Travaux: 3"]},{"dept":"34","score":49,"top":["Bouchons: 1","Incidents: 9","Travaux: 6"]},{"dept":"38","score":48,"top":["Bouchons: 3","Incidents: 6","Travaux: 6"]},{"dept":"48","score":48,"top":["Incidents: 4","Travaux: 7","Prévu (24h): 3"]},{"dept":"63","score":48,"top":["Incidents: 6","Travaux: 9"]},{"dept":"89","score":48,"top":["Incidents: 8","Travaux: 7"]},{"dept":"73","score":47,"top":["Incidents: 14","Travaux: 5"]},{"dept":"28","score":46,"top":["Incidents: 7","Travaux: 10"]},{"dept":"30","score":46,"top":["Bouchons: 1","Incidents: 3","Travaux: 4"]},{"dept":"35","score":46,"top":["Incidents: 2","Travaux: 7"]},{"dept":"42","score":46,"top":["Incidents: 6","Travaux: 10"]},{"dept":"72","score":45,"top":["Incidents: 6","Travaux: 7"]}]}