{"generated_at":"2026-06-15T21:18:47.105901Z","source":"Bison Futé / TIPI (transport.data.gouv.fr recaps)","errors":[],"depts_detected":87,"top_depts_h24":[{"dept":"04","score":100,"top":["Incidents: 16","Travaux: 7"]},{"dept":"05","score":100,"top":["Incidents: 29","Travaux: 2","Prévu (24h): 2"]},{"dept":"06","score":100,"top":["Incidents: 11","Travaux: 8"]},{"dept":"13","score":100,"top":["Incidents: 8","Travaux: 15","Prévu (24h): 3"]},{"dept":"17","score":100,"top":["Incidents: 9","Travaux: 4"]},{"dept":"30","score":100,"top":["Incidents: 4","Travaux: 6","Prévu (24h): 4"]},{"dept":"33","score":100,"top":["Incidents: 10","Travaux: 18","Prévu (24h): 1"]},{"dept":"35","score":100,"top":["Incidents: 2","Travaux: 13","Prévu (24h): 3"]},{"dept":"38","score":100,"top":["Incidents: 4","Travaux: 10"]},{"dept":"59","score":100,"top":["Incidents: 7","Travaux: 12"]},{"dept":"61","score":100,"top":["Incidents: 12","Travaux: 1"]},{"dept":"69","score":100,"top":["Incidents: 4","Travaux: 8"]},{"dept":"73","score":100,"top":["Incidents: 12","Travaux: 3"]},{"dept":"74","score":100,"top":["Incidents: 5","Travaux: 10"]},{"dept":"77","score":100,"top":["Incidents: 5","Travaux: 11"]},{"dept":"83","score":100,"top":["Incidents: 23","Travaux: 15"]},{"dept":"56","score":95,"top":["Incidents: 5","Travaux: 5","Prévu (24h): 1"]},{"dept":"62","score":94,"top":["Incidents: 4","Travaux: 7"]},{"dept":"42","score":86,"top":["Incidents: 5","Travaux: 4"]},{"dept":"58","score":86,"top":["Incidents: 5","Travaux: 4"]}],"top_depts_h48":[{"dept":"04","score":100,"top":["Incidents: 16","Travaux: 7"]},{"dept":"05","score":100,"top":["Incidents: 29","Travaux: 2","Prévu (24h): 2"]},{"dept":"13","score":100,"top":["Incidents: 8","Travaux: 15","Prévu (24h): 3"]},{"dept":"33","score":100,"top":["Incidents: 10","Travaux: 18","Prévu (24h): 1"]},{"dept":"83","score":100,"top":["Incidents: 23","Travaux: 15"]},{"dept":"06","score":79,"top":["Incidents: 11","Travaux: 8"]},{"dept":"35","score":75,"top":["Incidents: 2","Travaux: 13","Prévu (24h): 3"]},{"dept":"59","score":70,"top":["Incidents: 7","Travaux: 12"]},{"dept":"74","score":68,"top":["Incidents: 5","Travaux: 10"]},{"dept":"77","score":66,"top":["Incidents: 5","Travaux: 11"]},{"dept":"30","score":60,"top":["Incidents: 4","Travaux: 6","Prévu (24h): 4"]},{"dept":"38","score":52,"top":["Incidents: 4","Travaux: 10"]},{"dept":"17","score":50,"top":["Incidents: 9","Travaux: 4"]},{"dept":"31","score":50,"top":["Incidents: 3","Travaux: 7","Prévu (24h): 1"]},{"dept":"69","score":48,"top":["Incidents: 4","Travaux: 8"]},{"dept":"73","score":46,"top":["Incidents: 12","Travaux: 3"]},{"dept":"56","score":45,"top":["Incidents: 5","Travaux: 5","Prévu (24h): 1"]},{"dept":"62","score":44,"top":["Incidents: 4","Travaux: 7"]},{"dept":"44","score":42,"top":["Incidents: 4","Travaux: 5","Prévu (24h): 1"]},{"dept":"48","score":42,"top":["Incidents: 2","Travaux: 5","Prévu (24h): 3"]}],"top_depts_h72":[{"dept":"05","score":100,"top":["Incidents: 29","Travaux: 2","Prévu (24h): 2"]},{"dept":"83","score":100,"top":["Incidents: 23","Travaux: 15"]},{"dept":"33","score":99,"top":["Incidents: 10","Travaux: 18","Prévu (24h): 1"]},{"dept":"13","score":83,"top":["Incidents: 8","Travaux: 15","Prévu (24h): 3"]},{"dept":"04","score":81,"top":["Incidents: 16","Travaux: 7"]},{"dept":"35","score":64,"top":["Incidents: 2","Travaux: 13","Prévu (24h): 3"]},{"dept":"06","score":63,"top":["Incidents: 11","Travaux: 8"]},{"dept":"59","score":56,"top":["Incidents: 7","Travaux: 12"]},{"dept":"74","score":54,"top":["Incidents: 5","Travaux: 10"]},{"dept":"77","score":53,"top":["Incidents: 5","Travaux: 11"]},{"dept":"30","score":52,"top":["Incidents: 4","Travaux: 6","Prévu (24h): 4"]},{"dept":"38","score":41,"top":["Incidents: 4","Travaux: 10"]},{"dept":"17","score":40,"top":["Incidents: 9","Travaux: 4"]},{"dept":"31","score":40,"top":["Incidents: 3","Travaux: 7","Prévu (24h): 1"]},{"dept":"69","score":39,"top":["Incidents: 4","Travaux: 8"]},{"dept":"44","score":38,"top":["Incidents: 4","Travaux: 5","Prévu (24h): 1"]},{"dept":"56","score":36,"top":["Incidents: 5","Travaux: 5","Prévu (24h): 1"]},{"dept":"73","score":36,"top":["Incidents: 12","Travaux: 3"]},{"dept":"62","score":35,"top":["Incidents: 4","Travaux: 7"]},{"dept":"48","score":33,"top":["Incidents: 2","Travaux: 5","Prévu (24h): 3"]}]}